tidylinq/__init__.py
tidylinq/functional.py
tidylinq/linq.py
tidylinq/model_inference.py
tidylinq/py.typed
tidylinq-0.2.0.dist-info/METADATA
tidylinq-0.2.0.dist-info/WHEEL
tidylinq-0.2.0.dist-info/entry_points.txt
tidylinq-0.2.0.dist-info/licenses/LICENSE
tidylinq-0.2.0.dist-info/RECORD
