Metadata-Version: 2.4
Name: tidylinq
Version: 0.2.0
Summary: Convenient LINQ-style table functions.
Project-URL: Repository, https://github.com/rjpower/tidylinq
Author-email: Russell Power <power@wasabilabs.ai>
License-Expression: MIT
License-File: LICENSE
Classifier: Development Status :: 4 - Beta
Classifier: Intended Audience :: Developers
Classifier: Operating System :: OS Independent
Classifier: Programming Language :: Python
Classifier: Programming Language :: Python :: 3
Classifier: Programming Language :: Python :: 3.11
Classifier: Programming Language :: Python :: 3.12
Classifier: Programming Language :: Python :: 3.13
Classifier: Typing :: Typed
Requires-Python: <4.0,>=3.11
Requires-Dist: pydantic>=2.11.7
Requires-Dist: tdqm>=0.0.1
